{
	"characters": [
		{
			"name": "CHeFs: Nona Lillius",
			"uri": "m2-nona-lillius.json"
		},
		{
			"name": "CHeFs: Deci Vitellius II",
			"uri": "m2-deci-vitellius.json"
		},
		{
			"name": "CHeFs: Hostus Juventus, Senior",
			"uri": "m2-hostus-juventus-senior.json"
		},
		{
			"name": "Majesty's Secret Service: Makval",
			"uri": "m2-makval.json"
		},
		{
			"name": "Solomani Front: Calypso",
			"uri": "m2-calypso.json"
		},
		{
			"name": "Solomani Front: Edmore Gray",
			"uri": "m2-edmore-gray.json"
		},
		{
			"name": "Solomani Front: Katya Almaty",
			"uri": "m2-katya-almaty.json"
		},
		{
			"name": "Solomani Front: Moonchild",
			"uri": "m2-moonchild.json"
		},
		{
			"name": "Solomani Front: Muemana",
			"uri": "m2-muemana.json"
		},
		{
			"name": "Solomani Front: Myra Berwick",
			"uri": "m2-myra-berwick.json"
		},
		{
			"name": "Solomani Front: Rille Iquiek",
			"uri": "m2-rille-iquiek.json"
		},
		{
			"name": "Solomani Front: Siryalia Robespierre",
			"uri": "m2-siryalia-robespierre.json"
		},
		{
			"name": "Solomani Front: Usha Dasdatta",
			"uri": "m2-usha-dasdatta.json"
		},
		{
			"name": "Solomani Front: Yash Verma",
			"uri": "m2-yash-verma.json"
		},
		{
			"name": "Vargr Extents: Zeki",
			"uri": "m2-zeki.json"
		}
	]	
}
